p3dopenxr/__init__.py
p3dopenxr/actionset.py
p3dopenxr/config_view.py
p3dopenxr/instance.py
p3dopenxr/layer.py
p3dopenxr/p3dopenxr.py
p3dopenxr/projection_view.py
p3dopenxr/session.py
p3dopenxr/space.py
p3dopenxr/swapchain.py
p3dopenxr/system.py
p3dopenxr/version.py
panda3d_openxr-0.1.2.dist-info/METADATA
panda3d_openxr-0.1.2.dist-info/WHEEL
panda3d_openxr-0.1.2.dist-info/licenses/LICENSE
panda3d_openxr-0.1.2.dist-info/RECORD
