Metadata-Version: 2.3
Name: panda3d-openxr
Version: 0.1.2
Summary: OpenXR support for Panda3D
Project-URL: Repository, https://github.com/el-dee/panda3d-openxr
Project-URL: Bug Tracker, https://github.com/el-dee/panda3d-openxr/issues
Author-email: Laurent Deru <laurent.deru@gmail.com>
License:                                  Apache License
License-File: LICENSE
Classifier: Development Status :: 4 - Beta
Classifier: License :: OSI Approved :: Apache Software License
Classifier: Programming Language :: Python
Classifier: Topic :: Multimedia :: Graphics :: 3D Rendering
Requires-Python: >=3.8
Requires-Dist: panda3d>=1.10.0
Requires-Dist: pyopengl>=3.0.0
Requires-Dist: pyopenxr>=1.1.0
